aya/__init__.py
poshy-2.1.data/scripts/poshy
poshy-2.1.dist-info/LICENSE
poshy-2.1.dist-info/METADATA
poshy-2.1.dist-info/WHEEL
poshy-2.1.dist-info/top_level.txt
poshy-2.1.dist-info/RECORD
