Metadata-Version: 2.1
Name: poshy
Version: 2.1
Summary: An extensible shell written in python
License: UNKNOWN
Platform: UNKNOWN
License-File: LICENSE
